dreemui/__init__.py
dreemui/dreemui.py
dreemui-0.1.0.dist-info/METADATA
dreemui-0.1.0.dist-info/WHEEL
dreemui-0.1.0.dist-info/top_level.txt
dreemui-0.1.0.dist-info/RECORD
