Metadata-Version: 2.1
Name: dreemui
Version: 0.1.0
Summary: A simple library to scrape and download websites
Home-page: https://github.com/yourusername/dreemui
Author: Dhrvu Ahir
Author-email: incnogeto@gmail.com
Classifier: Programming Language :: Python :: 3
Classifier: License :: OSI Approved :: MIT License
Classifier: Operating System :: OS Independent
Requires-Python: >=3.6
Requires-Dist: requests
Requires-Dist: beautifulsoup4
